cv_xtractor/__init__.py
cv_xtractor/extract_entities.py
cv_xtractor/jz_skill_patterns.jsonl
cv_xtractor-0.3.0.dist-info/LICENSE
cv_xtractor-0.3.0.dist-info/METADATA
cv_xtractor-0.3.0.dist-info/WHEEL
cv_xtractor-0.3.0.dist-info/top_level.txt
cv_xtractor-0.3.0.dist-info/RECORD
