Metadata-Version: 2.1
Name: cv_xtractor
Version: 0.3.0
Summary: A Python package for extracting information from CVs (resumes).
Home-page: https://github.com/remotown/CV-XTRACTOR
Author: Odai Israel Ago
Author-email: agocoded@gmail.com
License-File: LICENSE
Requires-Dist: spacy
Requires-Dist: pdfplumber
Requires-Dist: python-docx
Requires-Dist: PyMuPDF
